pyinfernal/CMakeLists.txt
pyinfernal/__init__.py
pyinfernal/_strings.pxi
pyinfernal/cm.cpython-39-x86_64-linux-gnu.so
pyinfernal/cm.pyx
pyinfernal/exceptions.pxi
pyinfernal/infernal/__init__.py
pyinfernal/infernal/_base.py
pyinfernal/infernal/_cmsearch.py
pyinfernal/tests/__init__.py
pyinfernal/tests/test_doctest.py
pyinfernal/tests/utils.py
pyinfernal/tests/data/cms/5.c.cbm
pyinfernal/tests/data/cms/5.c.cm
pyinfernal/tests/data/cms/RF00029.cm
pyinfernal/tests/data/cms/RF00042.cm
pyinfernal/tests/data/cms/RF00107.cm
pyinfernal/tests/data/cms/RF00243.cm
pyinfernal/tests/data/cms/RF03523.cm
pyinfernal/tests/data/cms/tRNA.c.cbm
pyinfernal/tests/data/cms/tRNA.c.cm
pyinfernal/tests/data/seqs/pANT_R100.fa
pyinfernal/tests/data/tables/pANT.5c.Z0_1.tbl
pyinfernal/tests/data/tables/pANT.RF00029.Z0_1.tbl
pyinfernal/tests/data/tables/pANT.RF00042.Z0_1.tbl
pyinfernal/tests/data/tables/pANT.RF00107.Z0_1.tbl
pyinfernal/tests/data/tables/pANT.RF00243.Z0_1.tbl
pyinfernal/tests/data/tables/pANT.RF03523.Z0_1.tbl
pyinfernal/tests/data/tables/pANT.RFall.Z0_1.tbl
pyinfernal/tests/test_cm/__init__.py
pyinfernal/tests/test_cm/test_cmfile.py
pyinfernal/tests/test_infernal/__init__.py
pyinfernal/tests/test_infernal/test_cmsearch.py
pyinfernal.libs/liblibinfernal.so
pyinfernal.libs/include/libinfernal/__init__.pxd
pyinfernal.libs/include/libinfernal/cm.pxd
pyinfernal.libs/include/libinfernal/cm_alidisplay.pxd
pyinfernal.libs/include/libinfernal/cm_file.pxd
pyinfernal.libs/include/libinfernal/cm_modelconfig.pxd
pyinfernal.libs/include/libinfernal/cm_mx.pxd
pyinfernal.libs/include/libinfernal/cm_p7_modelconfig.pxd
pyinfernal.libs/include/libinfernal/cm_pipeline.pxd
pyinfernal.libs/include/libinfernal/cm_qdband.pxd
pyinfernal.libs/include/libinfernal/cm_tophits.pxd
pyinfernal.libs/include/libinfernal/cmsearch.pxd
pyinfernal.libs/include/libinfernal/config.h
pyinfernal.libs/include/libinfernal/cp9.pxd
pyinfernal-0.1.0.dist-info/METADATA
pyinfernal-0.1.0.dist-info/WHEEL
pyinfernal-0.1.0.dist-info/RECORD
pyinfernal-0.1.0.dist-info/licenses/COPYING
