Metadata-Version: 2.4
Name: pyinfernal
Version: 0.1.0
Summary: Cython bindings and Python interface to Infernal.
Keywords: bioinformatics,RNA,covariance model,CM,rfam
Author-Email: Martin Larralde <martin.larralde@embl.de>
License-Expression: MIT
License-File: COPYING
Classifier: Development Status :: 4 - Beta
Classifier: Intended Audience :: Developers
Classifier: Intended Audience :: Science/Research
Classifier: Operating System :: POSIX
Classifier: Programming Language :: C
Classifier: Programming Language :: Cython
Classifier: Programming Language :: Python :: 3.7
Classifier: Programming Language :: Python :: 3.8
Classifier: Programming Language :: Python :: 3.9
Classifier: Programming Language :: Python :: 3.10
Classifier: Programming Language :: Python :: 3.11
Classifier: Programming Language :: Python :: 3.12
Classifier: Programming Language :: Python :: 3.13
Classifier: Programming Language :: Python :: 3.14
Classifier: Programming Language :: Python :: Implementation :: CPython
Classifier: Programming Language :: Python :: Implementation :: PyPy
Classifier: Topic :: Scientific/Engineering :: Bio-Informatics
Classifier: Topic :: Scientific/Engineering :: Medical Science Apps.
Project-URL: Homepage, https://github.com/althonos/pyinfernal/
Project-URL: Documentation, https://pyinfernal.readthedocs.io/en/stable/
Project-URL: Bug Tracker, https://github.com/althonos/pyinfernal/issues
Project-URL: Changelog, https://github.com/althonos/pyinfernal/blob/master/CHANGELOG.md
Project-URL: Builds, https://github.com/althonos/pyinfernal/actions
Project-URL: PyPI, https://pypi.org/project/pyinfernal
Project-URL: PiWheels, https://piwheels.org/project/pyinfernal/
Requires-Python: >=3.7
Requires-Dist: pyhmmer~=0.12.0
Provides-Extra: test
Requires-Dist: importlib-resources; python_version < "3.9" and extra == "test"
